bzx/__init__.py
bzx/__main__.py
bzx/bzx.py
bzx-0.1.0.dist-info/LICENSE
bzx-0.1.0.dist-info/METADATA
bzx-0.1.0.dist-info/WHEEL
bzx-0.1.0.dist-info/top_level.txt
bzx-0.1.0.dist-info/RECORD
