Metadata-Version: 2.2
Name: bzx
Version: 0.1.0
Summary: A Python package for BOOZ_XFORM output to GKV input
Author-email: Shinya Maeyama <maeyama.shinya@nifs.ac.jp>
License: MIT License
Requires-Python: >=3.7
License-File: LICENSE
Requires-Dist: numpy>=1.23
Requires-Dist: scipy>=1.15
Requires-Dist: xarray>=2022.3
Provides-Extra: examples
Requires-Dist: matplotlib>=3.5; extra == "examples"
Requires-Dist: booz_xform>=0.0.8; extra == "examples"
